batteryhorse/__init__.py
batteryhorse/__main__.py
batteryhorse/encoder.py
batteryhorse/version.py
batteryhorse/nltk_data/corpora/wordnet/LICENSE
batteryhorse/nltk_data/corpora/wordnet/README
batteryhorse/nltk_data/corpora/wordnet/adj.exc
batteryhorse/nltk_data/corpora/wordnet/adv.exc
batteryhorse/nltk_data/corpora/wordnet/citation.bib
batteryhorse/nltk_data/corpora/wordnet/cntlist.rev
batteryhorse/nltk_data/corpora/wordnet/data.adj
batteryhorse/nltk_data/corpora/wordnet/data.adv
batteryhorse/nltk_data/corpora/wordnet/data.noun
batteryhorse/nltk_data/corpora/wordnet/data.verb
batteryhorse/nltk_data/corpora/wordnet/index.adj
batteryhorse/nltk_data/corpora/wordnet/index.adv
batteryhorse/nltk_data/corpora/wordnet/index.noun
batteryhorse/nltk_data/corpora/wordnet/index.sense
batteryhorse/nltk_data/corpora/wordnet/index.verb
batteryhorse/nltk_data/corpora/wordnet/lexnames
batteryhorse/nltk_data/corpora/wordnet/noun.exc
batteryhorse/nltk_data/corpora/wordnet/verb.exc
BatteryHorse-1.0.0.dist-info/LICENSE
BatteryHorse-1.0.0.dist-info/METADATA
BatteryHorse-1.0.0.dist-info/WHEEL
BatteryHorse-1.0.0.dist-info/entry_points.txt
BatteryHorse-1.0.0.dist-info/top_level.txt
BatteryHorse-1.0.0.dist-info/RECORD
