Metadata-Version: 2.1
Name: BatteryHorse
Version: 1.0.0
Summary: Encode and decode binary data to English sentences
Home-page: https://github.com/cstranex/batteryhorse
Author: Chris Stranex
Author-email: chris@stranex.com
License: Apache License, Version 2.0
Project-URL: Source Code, https://github.com/cstranex/batteryhorse
Platform: UNKNOWN
Classifier: Programming Language :: Python :: 3
Classifier: License :: OSI Approved :: Apache Software License
Classifier: Operating System :: OS Independent
Requires-Python: >=3.4
Requires-Dist: nltk
